LICENSE.txt
MANIFEST.in
README.md
requirements.txt
requirements_test.txt
setup.py
cf_configuration_exporter.egg-info/PKG-INFO
cf_configuration_exporter.egg-info/SOURCES.txt
cf_configuration_exporter.egg-info/dependency_links.txt
cf_configuration_exporter.egg-info/entry_points.txt
cf_configuration_exporter.egg-info/requires.txt
cf_configuration_exporter.egg-info/top_level.txt
exporter/__init__.py
exporter/config.py
exporter/exceptions.py
exporter/exporter.py
exporter/mutations.py
exporter/run.py
exporter/templates/manifest.j2
test/test_helper.py