Metadata-Version: 1.1
Name: cf-configuration-exporter
Version: 0.0.13
Summary: Simple utility to generate a configuration manifest from a live CloudFoundry installation
Home-page: https://github.com/SpringerPE/cf-configuration-exporter
Author: Claudio Benfatto
Author-email: claudio.benfatto@springer.com
License: MIT
Download-URL: https://github.com/SpringerPE/cf-configuration-exporter/releases/tag/v0.0.13
Keywords: cf cloudfoundry cloud foundry
Platform: UNKNOWN
Classifier: Development Status :: 3 - Alpha
Classifier: Intended Audience :: System Administrators
Classifier: Topic :: System :: Systems Administration
Classifier: License :: OSI Approved :: MIT License
Classifier: Programming Language :: Python :: 2.7
Classifier: Programming Language :: Python :: 3
